wolf_cli/__init__.py
wolf_cli/cli.py
wolf_cli/commands/__init__.py
wolf_cli/commands/images.py
wolf_cli/commands/urls.py
wolf_cli-0.0.4.dist-info/entry_points.txt
wolf_cli-0.0.4.dist-info/LICENSE
wolf_cli-0.0.4.dist-info/WHEEL
wolf_cli-0.0.4.dist-info/METADATA
wolf_cli-0.0.4.dist-info/RECORD
